cfutils/__init__.py
cfutils/align.py
cfutils/cli.py
cfutils/count.py
cfutils/parser.py
cfutils/run.py
cfutils/show.py
cfutils/utils.py
cfutils-0.0.0.dev61.dist-info/METADATA
cfutils-0.0.0.dev61.dist-info/WHEEL
cfutils-0.0.0.dev61.dist-info/entry_points.txt
cfutils-0.0.0.dev61.dist-info/RECORD
