Metadata-Version: 2.1
Name: cfutils
Version: 0.0.0.dev61
Summary: Chromatogram File Utils
Home-page: https://github.com/yech1990/cfutils
License: MIT
Keywords: DNA,mutation,chromatogram,biology
Author: Ye Chang
Author-email: yech1990@gmail.com
Requires-Python: >=3.9,<4.0
Classifier: License :: OSI Approved :: MIT License
Classifier: Programming Language :: Python :: 3
Classifier: Programming Language :: Python :: 3.9
Classifier: Programming Language :: Python :: 3.10
Classifier: Programming Language :: Python :: 3.11
Classifier: Programming Language :: Python :: 3.12
Classifier: Programming Language :: Python :: 3.13
Requires-Dist: click (>=8.0.0,<9.0.0)
Requires-Dist: matplotlib (>=3.9.2,<4.0.0)
Requires-Dist: ssw (>=0.4.1,<0.5.0)
Project-URL: Documentation, https://cf.readthedocs.io/
Project-URL: Repository, https://github.com/yech1990/cfutils
